{
  "Header": {
    "Copyright": "Copyright (c) 2001 - 2025 Intel Corporation. All rights reserved.",
    "Info": "PerfSpect Performance Monitoring Metrics for Intel(R) Xeon(R) 6 Processor with P-cores (Granite Rapids)"
  },
  "PerfmonMetricsFile": "resources:gnr/graniterapids_metrics.json",
  "PerfmonCoreEventsFile": "resources:gnr/graniterapids_core.json",
  "PerfmonUncoreEventsFile": "resources:gnr/graniterapids_uncore.json",
  "PerfmonRetireLatencyFile": "resources:gnr/graniterapids_retire_latency.json",
  "AlternateTMAMetricsFile": "resources:gnr/gnr_alt_tma_metrics.json",
  "PerfspectMetricsFile": "resources:gnr/gnr_perfspect_metrics.json",
  "ReportMetrics": [
    {
      "MetricName": "cpu_operating_frequency",
      "Origin": "perfmon"
    },
    {
      "MetricName": "cpu_utilization",
      "Origin": "perfmon"
    },
    {
      "MetricName": "cpu_util_kernel",
      "Origin": "perfspect"
    },
    {
      "MetricName": "cpi",
      "Origin": "perfmon"
    },
    {
      "MetricName": "cycles_per_txn",
      "Origin": "perfspect"
    },
    {
      "MetricName": "kernel_cpi",
      "Origin": "perfspect"
    },
    {
      "MetricName": "kernel_cycles_per_txn",
      "Origin": "perfspect"
    },
    {
      "MetricName": "ipc",
      "Origin": "perfspect"
    },
    {
      "MetricName": "giga_instructions_per_sec",
      "Origin": "perfspect"
    },
    {
      "MetricName": "branch_misprediction_ratio",
      "Origin": "perfspect"
    },
    {
      "MetricName": "locks_retired_per_instr",
      "Origin": "perfspect"
    },
    {
      "MetricName": "locks_retired_per_txn",
      "Origin": "perfspect"
    },
    {
      "MetricName": "l1d_mpi",
      "Origin": "perfmon"
    },
    {
      "MetricName": "l1d_misses_per_txn",
      "Origin": "perfspect"
    },
    {
      "MetricName": "l1d_demand_data_read_hits_per_instr",
      "Origin": "perfmon"
    },
    {
      "MetricName": "l1d_demand_data_read_hits_per_txn",
      "Origin": "perfspect"
    },
    {
      "MetricName": "l1_i_code_read_misses_with_prefetches_per_instr",
      "Origin": "perfmon"
    },
    {
      "MetricName": "l1i_code_read_misses_per_txn",
      "Origin": "perfspect"
    },
    {
      "MetricName": "l2_demand_data_read_hits_per_instr",
      "Origin": "perfmon"
    },
    {
      "MetricName": "l2_demand_data_read_hits_per_txn",
      "Origin": "perfspect"
    },
    {
      "MetricName": "l2_mpi",
      "Origin": "perfmon"
    },
    {
      "MetricName": "l2_misses_per_txn",
      "Origin": "perfspect"
    },
    {
      "MetricName": "l2_demand_data_read_mpi",
      "Origin": "perfmon"
    },
    {
      "MetricName": "l2_demand_data_read_misses_per_txn",
      "Origin": "perfspect"
    },
    {
      "MetricName": "l2_demand_code_mpi",
      "Origin": "perfmon"
    },
    {
      "MetricName": "l2_demand_code_misses_per_txn",
      "Origin": "perfspect"
    },
    {
      "MetricName": "llc_code_read_mpi_demand_plus_prefetch",
      "Origin": "perfmon"
    },
    {
      "MetricName": "llc_code_read_misses_per_txn",
      "Origin": "perfspect"
    },
    {
      "MetricName": "llc_data_read_mpi_demand_plus_prefetch",
      "Origin": "perfmon"
    },
    {
      "MetricName": "llc_data_read_misses_per_txn",
      "Origin": "perfspect"
    },
    {
      "MetricName": "llc_demand_data_read_miss_latency",
      "Origin": "perfmon"
    },
    {
      "MetricName": "llc_demand_data_read_miss_latency_for_local_requests",
      "Origin": "perfmon"
    },
    {
      "MetricName": "llc_demand_data_read_miss_latency_for_remote_requests",
      "Origin": "perfmon"
    },
    {
      "MetricName": "upi_data_transmit_bw",
      "Origin": "perfmon"
    },
    {
      "MetricName": "package_power",
      "Origin": "perfspect"
    },
    {
      "MetricName": "dram_power",
      "Origin": "perfspect"
    },
    {
      "MetricName": "core_c6_residency",
      "Origin": "perfspect"
    },
    {
      "MetricName": "package_c6_residency",
      "Origin": "perfspect"
    },
    {
      "MetricName": "percent_uops_delivered_from_decoded_icache",
      "Origin": "perfmon"
    },
    {
      "MetricName": "percent_uops_delivered_from_legacy_decode_pipeline",
      "Origin": "perfmon"
    },
    {
      "MetricName": "memory_bandwidth_read",
      "Origin": "perfmon"
    },
    {
      "MetricName": "memory_bandwidth_write",
      "Origin": "perfmon"
    },
    {
      "MetricName": "memory_bandwidth_total",
      "Origin": "perfmon"
    },
    {
      "MetricName": "itlb_2nd_level_mpi",
      "Origin": "perfmon"
    },
    {
      "MetricName": "itlb_misses_per_txn",
      "Origin": "perfspect"
    },
    {
      "MetricName": "dtlb_2nd_level_load_mpi",
      "Origin": "perfmon"
    },
    {
      "MetricName": "dtlb_load_misses_per_txn",
      "Origin": "perfspect"
    },
    {
      "MetricName": "dtlb_2nd_level_store_mpi",
      "Origin": "perfmon"
    },
    {
      "MetricName": "dtlb_store_misses_per_txn",
      "Origin": "perfspect"
    },
    {
      "MetricName": "numa_reads_addressed_to_local_dram",
      "Origin": "perfmon"
    },
    {
      "MetricName": "numa_reads_addressed_to_remote_dram",
      "Origin": "perfmon"
    },
    {
      "MetricName": "numa_percent_all_reads_to_local_cluster_memory",
      "Origin": "perfmon"
    },
    {
      "MetricName": "numa_percent_all_reads_to_remote_cluster_cache",
      "Origin": "perfmon"
    },
    {
      "MetricName": "numa_percent_all_reads_to_local_cluster_cache",
      "Origin": "perfmon"
    },
    {
      "MetricName": "uncore_frequency",
      "Origin": "perfmon"
    },
    {
      "MetricName": "io_bandwidth_write",
      "Origin": "perfmon"
    },
    {
      "MetricName": "io_bandwidth_read",
      "Origin": "perfmon"
    },
    {
      "MetricName": "Frontend_Bound",
      "Origin": "perfmon"
    },
    {
      "MetricName": "Fetch_Latency",
      "Origin": "perfmon"
    },
    {
      "MetricName": "ICache_Misses",
      "Origin": "perfmon"
    },
    {
      "MetricName": "ITLB_Misses",
      "Origin": "perfmon"
    },
    {
      "MetricName": "Branch_Resteers",
      "Origin": "perfmon"
    },
    {
      "MetricName": "MS_Switches",
      "Origin": "perfmon"
    },
    {
      "MetricName": "LCP",
      "Origin": "perfmon"
    },
    {
      "MetricName": "DSB_Switches",
      "Origin": "perfmon"
    },
    {
      "MetricName": "Fetch_Bandwidth",
      "Origin": "perfmon"
    },
    {
      "MetricName": "MITE",
      "Origin": "perfmon"
    },
    {
      "MetricName": "DSB",
      "Origin": "perfmon"
    },
    {
      "MetricName": "MS",
      "Origin": "perfmon"
    },
    {
      "MetricName": "Bad_Speculation",
      "Origin": "perfmon"
    },
    {
      "MetricName": "Branch_Mispredicts",
      "Origin": "perfmon"
    },
    {
      "MetricName": "Cond_NT_Mispredicts",
      "Origin": "perfmon"
    },
    {
      "MetricName": "Cond_TK_Mispredicts",
      "Origin": "perfmon"
    },
    {
      "MetricName": "Ind_Call_Mispredicts",
      "Origin": "perfmon"
    },
    {
      "MetricName": "Ind_Jump_Mispredicts",
      "Origin": "perfmon"
    },
    {
      "MetricName": "Ret_Mispredicts",
      "Origin": "perfmon"
    },
    {
      "MetricName": "Other_Mispredicts",
      "Origin": "perfmon"
    },
    {
      "MetricName": "Machine_Clears",
      "Origin": "perfmon"
    },
    {
      "MetricName": "Other_Nukes",
      "Origin": "perfmon"
    },
    {
      "MetricName": "Backend_Bound",
      "Origin": "perfmon"
    },
    {
      "MetricName": "Memory_Bound",
      "Origin": "perfmon"
    },
    {
      "MetricName": "L1_Bound",
      "Origin": "perfmon"
    },
    {
      "MetricName": "DTLB_Load",
      "Origin": "perfmon"
    },
    {
      "MetricName": "Store_Fwd_Blk",
      "Origin": "perfmon"
    },
    {
      "MetricName": "L1_Latency_Dependency",
      "Origin": "perfmon"
    },
    {
      "MetricName": "Lock_Latency",
      "Origin": "perfmon"
    },
    {
      "MetricName": "Split_Loads",
      "Origin": "perfmon"
    },
    {
      "MetricName": "FB_Full",
      "Origin": "perfmon"
    },
    {
      "MetricName": "L2_Bound",
      "Origin": "perfmon"
    },
    {
      "MetricName": "L3_Bound",
      "Origin": "perfmon"
    },
    {
      "MetricName": "Contested_Accesses",
      "Origin": "perfmon"
    },
    {
      "MetricName": "Data_Sharing",
      "Origin": "perfmon"
    },
    {
      "MetricName": "L3_Hit_Latency",
      "Origin": "perfmon"
    },
    {
      "MetricName": "SQ_Full",
      "Origin": "perfmon"
    },
    {
      "MetricName": "DRAM_Bound",
      "Origin": "perfmon"
    },
    {
      "MetricName": "MEM_Bandwidth",
      "Origin": "perfmon"
    },
    {
      "MetricName": "MEM_Latency",
      "Origin": "perfmon"
    },
    {
      "MetricName": "Store_Bound",
      "Origin": "perfmon"
    },
    {
      "MetricName": "Store_Latency",
      "Origin": "perfmon"
    },
    {
      "MetricName": "False_Sharing",
      "Origin": "perfmon"
    },
    {
      "MetricName": "Split_Stores",
      "Origin": "perfmon"
    },
    {
      "MetricName": "Streaming_Stores",
      "Origin": "perfmon"
    },
    {
      "MetricName": "DTLB_Store",
      "Origin": "perfmon"
    },
    {
      "MetricName": "Core_Bound",
      "Origin": "perfmon"
    },
    {
      "MetricName": "Divider",
      "Origin": "perfmon"
    },
    {
      "MetricName": "Serializing_Operation",
      "Origin": "perfmon"
    },
    {
      "MetricName": "AMX_Busy",
      "Origin": "perfmon"
    },
    {
      "MetricName": "Ports_Utilization",
      "Origin": "perfmon"
    },
    {
      "MetricName": "Retiring",
      "Origin": "perfmon"
    },
    {
      "MetricName": "Light_Operations",
      "Origin": "perfmon"
    },
    {
      "MetricName": "FP_Arith",
      "Origin": "perfmon"
    },
    {
      "MetricName": "Int_Operations",
      "Origin": "perfmon"
    },
    {
      "MetricName": "Memory_Operations",
      "Origin": "perfmon"
    },
    {
      "MetricName": "Fused_Instructions",
      "Origin": "perfmon"
    },
    {
      "MetricName": "Non_Fused_Branches",
      "Origin": "perfmon"
    },
    {
      "MetricName": "Other_Light_Ops",
      "Origin": "perfmon"
    },
    {
      "MetricName": "Heavy_Operations",
      "Origin": "perfmon"
    },
    {
      "MetricName": "Few_Uops_Instructions",
      "Origin": "perfmon"
    },
    {
      "MetricName": "Microcode_Sequencer",
      "Origin": "perfmon"
    }
  ]
}